cicc_colors/__init__.py
cicc_colors/colors.py
cicc_colors-0.3.1.dist-info/LICENSE
cicc_colors-0.3.1.dist-info/METADATA
cicc_colors-0.3.1.dist-info/WHEEL
cicc_colors-0.3.1.dist-info/top_level.txt
cicc_colors-0.3.1.dist-info/RECORD
