Metadata-Version: 2.1
Name: cicc-colors
Version: 0.3.1
Summary: Library of color palettes for CICC WM slides, reports and tables.
Home-page: https://github.com/nyuspc/cicc_colors
Author: Pengcheng Song
Author-email: smth_spc@hotmail.com
License: UNKNOWN
Platform: UNKNOWN
Classifier: Programming Language :: Python
Classifier: Intended Audience :: Financial and Insurance Industry
Classifier: Topic :: Multimedia :: Graphics
Classifier: License :: OSI Approved :: MIT License
Classifier: Operating System :: OS Independent
